{
    "Angka dan Bilangan": [
        ["一", "いち", "satu"],
        ["二", "に", "dua"],
        ["三", "さん", "tiga"],
        ["四", "し、よん", "empat"],
        ["五", "ご", "lima"],
        ["六", "ろく", "enam"],
        ["七", "しち、なな", "tujuh"],
        ["八", "はち", "delapan"],
        ["九", "きゅう、く", "sembilan"],
        ["十", "じゅう", "sepuluh"],
        ["百", "ひゃく", "seratus"],
        ["千", "せん", "seribu"],
        ["万", "まん", "sepuluh ribu"]
    ],
    "Waktu dan Kalender": [
        ["時", "じ", "waktu, jam"],
        ["分", "ふん、ぶん", "menit, bagian"],
        ["半", "はん", "setengah"],
        ["今", "いま", "sekarang"],
        ["先", "さき", "sebelum, depan"],
        ["年", "とし", "tahun"],
        ["週", "しゅう", "minggu"],
        ["朝", "あさ", "pagi"],
        ["昼", "ひる", "siang"],
        ["夕", "ゆう", "sore"],
        ["夜", "よる", "malam"],
        ["曜", "よう", "hari dalam minggu"]
    ],
    "Alam dan Cuaca": [
        ["山", "やま", "gunung"],
        ["川", "かわ", "sungai"],
        ["木", "き", "pohon"],
        ["花", "はな", "bunga"],
        ["草", "くさ", "rumput"],
        ["空", "そら", "langit"],
        ["天", "てん", "langit, surga"],
        ["日", "ひ、にち", "matahari, hari"],
        ["月", "つき", "bulan"],
        ["火", "ひ", "api"],
        ["水", "みず", "air"],
        ["土", "つち", "tanah"],
        ["風", "かぜ", "angin"],
        ["雨", "あめ", "hujan"],
        ["雪", "ゆき", "salju"]
    ],
    "Arah dan Posisi": [
        ["左", "ひだり", "kiri"],
        ["右", "みぎ", "kanan"],
        ["上", "うえ", "atas"],
        ["下", "した", "bawah"],
        ["中", "なか", "dalam, tengah"],
        ["外", "そと", "luar"],
        ["前", "まえ", "depan"],
        ["後", "あと、うしろ", "setelah, belakang"],
        ["近", "ちかい", "dekat"],
        ["遠", "とおい", "jauh"]
    ],
    "Tubuh Manusia": [
        ["人", "ひと", "orang"],
        ["子", "こ", "anak"],
        ["女", "おんな", "perempuan"],
        ["男", "おとこ", "laki-laki"],
        ["目", "め", "mata"],
        ["耳", "みみ", "telinga"],
        ["口", "くち", "mulut"],
        ["手", "て", "tangan"],
        ["足", "あし", "kaki"],
        ["体", "からだ", "tubuh"],
        ["頭", "あたま", "kepala"],
        ["心", "こころ", "hati"],
        ["声", "こえ", "suara"]
    ],
    "Warna": [
        ["白", "しろ", "putih"],
        ["黒", "くろ", "hitam"],
        ["赤", "あか", "merah"],
        ["青", "あお", "biru"],
        ["黄", "き", "kuning"],
        ["色", "いろ", "warna"]
    ],
"Aktivitas Sehari-hari": [
    ["見る", "みる", "melihat"],
    ["行く", "いく", "pergi"],
    ["来る", "くる", "datang"],
    ["帰る", "かえる", "pulang"],
    ["食べる", "たべる", "makan"],
    ["飲む", "のむ", "minum"],
    ["立つ", "たつ", "berdiri"],
    ["走る", "はしる", "berlari"],
    ["入る", "はいる", "masuk"],
    ["出る", "でる", "keluar"],
    ["買う", "かう", "membeli"],
    ["売る", "うる", "menjual"],
    ["書く", "かく", "menulis"],
    ["読む", "よむ", "membaca"],
    ["聞く", "きく", "mendengar / bertanya"],
    ["話す", "はなす", "berbicara"],
    ["使う", "つかう", "menggunakan"],
    ["作る", "つくる", "membuat"],
    ["洗う", "あらう", "mencuci"],
    ["起きる", "おきる", "bangun"],
    ["寝る", "ねる", "tidur"],
    ["働く", "はたらく", "bekerja"],
    ["休む", "やすむ", "beristirahat / absen"],
    ["開ける", "あける", "membuka"],
    ["閉める", "しめる", "menutup"]
],
    "Pendidikan dan Pekerjaan": [
        ["学", "がく", "belajar"],
        ["校", "こう", "sekolah"],
        ["教", "おしえる", "mengajar"],
        ["習", "ならう", "belajar"],
        ["勉", "べん", "usaha keras"],
        ["業", "ぎょう", "pekerjaan"],
        ["仕", "し", "tugas"],
        ["会", "あう", "bertemu"],
        ["社", "しゃ", "perusahaan"]
    ],
"Transportasi dan Perjalanan": [
    ["旅", "たび", "perjalanan"],
    ["駅", "えき", "stasiun"],
    ["車", "くるま", "mobil"],
    ["道", "みち", "jalan"],
    ["送", "おくる", "mengirim"],
    ["転", "ころぶ", "terjatuh / terguling (berputar, terkait kendaraan)"],
    ["走", "はしる", "berlari / berjalan (kendaraan juga bisa)"],
    ["通", "とおる", "melewati / melintasi"],
    ["着", "つく", "tiba (di tempat)"],
    ["発", "はつ", "berangkat (biasanya sebagai bagian kata 発車, 出発 dll)"]
],
    "Tempat dan Bangunan": [
        ["店", "みせ", "toko"],
        ["銀", "ぎん", "perak"],
        ["病", "びょう", "penyakit"],
        ["医", "い", "medis"],
        ["席", "せき", "kursi"],
        ["町", "まち", "kota kecil"],
        ["村", "むら", "desa"],
        ["京", "きょう", "ibu kota"],
        ["池", "いけ", "kolam"],
        ["海", "うみ", "laut"]
    ],
"Perasaan dan Keadaan": [
    ["明るい", "あかるい", "terang"],
    ["楽しい", "たのしい", "menyenangkan"],
    ["強い", "つよい", "kuat"],
    ["弱い", "よわい", "lemah"],
    ["高い", "たかい", "tinggi, mahal"],
    ["低い", "ひくい", "rendah"],
    ["長い", "ながい", "panjang"],
    ["短い", "みじかい", "pendek"],
    ["新しい", "あたらしい", "baru"],
    ["古い", "ふるい", "lama"],
    ["思う", "おもう", "berpikir"],
    ["知る", "しる", "mengetahui"],
    ["無い", "ない", "tidak ada"],
    ["理由", "りゆう", "alasan"],
    ["進む", "すすむ", "maju"],
    ["退く", "しりぞく", "mundur"],   
    ["怖い", "こわい", "menakutkan"],
    ["悲しい", "かなしい", "sedih"],
    ["嬉しい", "うれしい", "senang"],
    ["恥ずかしい", "はずかしい", "malu"],
    ["心配", "しんぱい", "khawatir"],
    ["大丈夫", "だいじょうぶ", "tidak apa-apa / baik-baik saja"],
    ["安心", "あんしん", "lega / tenang"],
    ["不安", "ふあん", "cemas / tidak tenang"],
    ["大変", "たいへん", "sulit / berat / gawat"],
    ["便利", "べんり", "praktis"],
    ["不便", "ふべん", "tidak praktis"],
    ["自由", "じゆう", "bebas"]
],
    "Kegiatan dan Perubahan": [
        ["開", "ひらく", "membuka"],
        ["閉", "しめる", "menutup"],
        ["受", "うける", "menerima"],
        ["終", "おわる", "selesai"],
        ["返", "かえす", "mengembalikan"]
    ],
    "Kompetisi dan Kehidupan": [
        ["勝", "かつ", "menang"],
        ["負", "まける", "kalah"],
        ["生", "いきる", "hidup"],
        ["死", "しぬ", "mati"],
        ["愛", "あい", "cinta"]
    ]
}
